aesthetic_predictor/__init__.py
aesthetic_predictor/libs.py
aesthetic_predictor-0.1.2.dist-info/METADATA
aesthetic_predictor-0.1.2.dist-info/WHEEL
aesthetic_predictor-0.1.2.dist-info/RECORD
