Metadata-Version: 2.1
Name: aesthetic-predictor
Version: 0.1.2
Summary: A python package of aesthetic quality of pictures a.k.a `aesthic-predictor`.
Home-page: https://github.com/elda27/aesthetic-predictor
License: MIT
Author: elda27
Author-email: kaz.birdstick@gmail.com
Requires-Python: >=3.8,<4.0
Classifier: License :: OSI Approved :: MIT License
Classifier: Programming Language :: Python :: 3
Classifier: Programming Language :: Python :: 3.8
Classifier: Programming Language :: Python :: 3.9
Classifier: Programming Language :: Python :: 3.10
Classifier: Programming Language :: Python :: 3.11
Classifier: Programming Language :: Python :: 3.12
Requires-Dist: open-clip-torch (>=2.16.0,<3.0.0)
Requires-Dist: torch (>1.13.1)
Project-URL: Repository, https://github.com/elda27/aesthetic-predictor
